{"status":"0","timestamp":"10:50am","stops":[{"latitude":43.041356,"stopID":"8496","intersection":"McKenna & Morraine View","destination":"Southbound","longitude":-89.505043},{"latitude":43.046311,"stopID":"8427","intersection":"Schroeder & White Oaks","destination":"Eastbound","longitude":-89.484384},{"latitude":43.049491,"stopID":"2522","intersection":"Whitney & Odana","destination":"Southbound","longitude":-89.473676},{"latitude":43.050661,"stopID":"2665","intersection":"Whitney & Odana","destination":"Northbound","longitude":-89.47332},{"latitude":43.04993,"stopID":"8124","intersection":"Gammon & Watts","destination":"Southbound","longitude":-89.503317},{"latitude":43.036049,"stopID":"8528","intersection":"McKenna & Park Heights","destination":"Southbound","longitude":-89.497271},{"latitude":43.044315,"stopID":"8274","intersection":"Whitney & Gilbert","destination":"Westbound","longitude":-89.474105},{"latitude":43.039362,"stopID":"8452","intersection":"Whitney & Hammersley","destination":"Southbound","longitude":-89.477752},{"latitude":43.046582,"stopID":"8181","intersection":"Struck & Schroeder","destination":"Northbound","longitude":-89.496474},{"latitude":43.036595,"stopID":"8685","intersection":"Whitney & Tolman","destination":"Northbound","longitude":-89.477416},{"latitude":43.038637,"stopID":"8166","intersection":"McKenna & Hammersley","destination":"Westbound","longitude":-89.500038},{"latitude":43.032145,"stopID":"8281","intersection":"McKenna & Raymond","destination":"Northbound","longitude":-89.496795},{"latitude":43.03196,"stopID":"8872","intersection":"Raymond & Frisch","destination":"Westbound","longitude":-89.493853},{"latitude":43.032046,"stopID":"8512","intersection":"Raymond & Whitney","destination":"Westbound","longitude":-89.477532},{"latitude":43.049818,"stopID":"8650","intersection":"Struck & Watts","destination":"Southbound","longitude":-89.496024},{"latitude":43.046367,"stopID":"8150","intersection":"Schroeder & Kessel","destination":"Westbound","longitude":-89.480763},{"latitude":43.053874,"stopID":"6100","intersection":"West Transfer Point","destination":"Eastbound","longitude":-89.47553},{"latitude":43.044054,"stopID":"8605","intersection":"Whitney & Gilbert","destination":"Eastbound","longitude":-89.473856},{"latitude":43.048648,"stopID":"2383","intersection":"Whitney & Medical","destination":"Northbound","longitude":-89.47333},{"latitude":43.03943,"stopID":"8160","intersection":"McKenna & Gammon","destination":"Westbound","longitude":-89.503726},{"latitude":43.050211,"stopID":"8582","intersection":"Watts & Struck","destination":"Westbound","longitude":-89.496173},{"latitude":43.051809,"stopID":"2324","intersection":"Whitney & Westgate","destination":"Southbound","longitude":-89.473671},{"latitude":43.046524,"stopID":"8131","intersection":"Gammon & Schroeder","destination":"Northbound","longitude":-89.503072},{"latitude":43.032055,"stopID":"8712","intersection":"Raymond & Leland","destination":"Westbound","longitude":-89.480041},{"latitude":43.046263,"stopID":"8219","intersection":"Schroeder & Rayovac","destination":"Eastbound","longitude":-89.491247},{"latitude":43.031831,"stopID":"8401","intersection":"Raymond & Cameron","destination":"Eastbound","longitude":-89.483414},{"latitude":43.046384,"stopID":"8146","intersection":"Schroeder & Chapel Hill","destination":"Westbound","longitude":-89.494074},{"latitude":43.033657,"stopID":"8796","intersection":"Whitney & Bartlett","destination":"Southbound","longitude":-89.47722},{"latitude":43.044202,"stopID":"8769","intersection":"Gammon & Gammon","destination":"Northbound","longitude":-89.503454},{"latitude":43.041377,"stopID":"8301","intersection":"McKenna & Morraine View","destination":"Northbound","longitude":-89.504826},{"latitude":43.045897,"stopID":"8180","intersection":"Gammon & Schroeder","destination":"Southbound","longitude":-89.503357},{"latitude":43.046484,"stopID":"8310","intersection":"Struck & Schroeder","destination":"Southbound","longitude":-89.496588},{"latitude":43.031702,"stopID":"8101","intersection":"Raymond & Prairie","destination":"Eastbound","longitude":-89.488529},{"latitude":43.050283,"stopID":"8918","intersection":"Watts & Woodmans","destination":"Westbound","longitude":-89.501026},{"latitude":43.039184,"stopID":"8513","intersection":"McKenna & Gammon","destination":"Eastbound","longitude":-89.503139},{"latitude":43.046286,"stopID":"8237","intersection":"Schroeder & Hathaway","destination":"Eastbound","longitude":-89.48845},{"latitude":43.031803,"stopID":"8363","intersection":"Raymond & Leland","destination":"Eastbound","longitude":-89.479959},{"latitude":43.046239,"stopID":"8531","intersection":"Schroeder & Chapel Hill","destination":"Eastbound","longitude":-89.494087},{"latitude":43.046371,"stopID":"8514","intersection":"Schroeder & Rayovac","destination":"Westbound","longitude":-89.491702},{"latitude":43.046404,"stopID":"8814","intersection":"Schroeder & Schroeder","destination":"Westbound","longitude":-89.477608},{"latitude":43.046328,"stopID":"8235","intersection":"Schroeder & Saybrook","destination":"Eastbound","longitude":-89.479373},{"latitude":43.031673,"stopID":"8709","intersection":"Raymond & Frisch","destination":"Eastbound","longitude":-89.493266},{"latitude":43.041911,"stopID":"8138","intersection":"Whitney & Piping Rock","destination":"Westbound","longitude":-89.477547},{"latitude":43.037014,"stopID":"8118","intersection":"Whitney & Tolman","destination":"Southbound","longitude":-89.47776},{"latitude":43.035887,"stopID":"8565","intersection":"McKenna & Park Heights","destination":"Northbound","longitude":-89.496918},{"latitude":43.031617,"stopID":"8779","intersection":"Raymond & McKenna","destination":"Eastbound","longitude":-89.496622},{"latitude":43.0501,"stopID":"8119","intersection":"Watts & Gammon","destination":"Eastbound","longitude":-89.502701},{"latitude":43.046425,"stopID":"8862","intersection":"Schroeder & White Oaks","destination":"Westbound","longitude":-89.48436},{"latitude":43.038474,"stopID":"8759","intersection":"McKenna & Hammersley","destination":"Eastbound","longitude":-89.500019},{"latitude":43.046317,"stopID":"8247","intersection":"Schroeder & Schroeder","destination":"Eastbound","longitude":-89.47775},{"latitude":43.045827,"stopID":"8418","intersection":"Whitney & Schroeder","destination":"Southbound","longitude":-89.473669},{"latitude":43.032182,"stopID":"8297","intersection":"Whitney & Raymond","destination":"Northbound","longitude":-89.476562},{"latitude":43.032064,"stopID":"8352","intersection":"Raymond & Cameron","destination":"Westbound","longitude":-89.482878},{"latitude":43.032032,"stopID":"8100","intersection":"Raymond & Prairie","destination":"Westbound","longitude":-89.489123},{"latitude":43.050175,"stopID":"8409","intersection":"Watts & Woodmans","destination":"Eastbound","longitude":-89.500996},{"latitude":43.034151,"stopID":"8341","intersection":"Whitney & Bartlett","destination":"Northbound","longitude":-89.477094},{"latitude":43.039442,"stopID":"8173","intersection":"Whitney & Hammersley","destination":"Northbound","longitude":-89.477369},{"latitude":43.046384,"stopID":"8370","intersection":"Schroeder & Hathaway","destination":"Westbound","longitude":-89.488667},{"latitude":43.041913,"stopID":"8633","intersection":"Whitney & Piping Rock","destination":"Eastbound","longitude":-89.477063}],"routeID":"50"}